django_health_check_version/__init__.py
django_health_check_version/apps.py
django_health_check_version/backends.py
django_health_check_version-1.0.0.dist-info/LICENSE.txt
django_health_check_version-1.0.0.dist-info/METADATA
django_health_check_version-1.0.0.dist-info/WHEEL
django_health_check_version-1.0.0.dist-info/top_level.txt
django_health_check_version-1.0.0.dist-info/RECORD
