Metadata-Version: 2.1
Name: django-health-check-version
Version: 1.0.0
Summary: Display settings.py VERSION in django-health-check output
Home-page: https://github.com/saschwarz/django-health-check-version
Author: Steve Schwarz
Author-email: steve@agilitynerd.com
License: UNKNOWN
Platform: UNKNOWN
Classifier: Programming Language :: Python :: 3
Classifier: License :: OSI Approved :: MIT License
Classifier: Operating System :: OS Independent
Requires-Python: >=3.7
License-File: LICENSE.txt
